zxftools/__init__.py
zxftools/file.py
zxftools/function.py
zxftools/llm.py
zxftools-0.1.6.dist-info/METADATA
zxftools-0.1.6.dist-info/WHEEL
zxftools-0.1.6.dist-info/top_level.txt
zxftools-0.1.6.dist-info/RECORD
