Metadata-Version: 2.1
Name: zxftools
Version: 0.1.6
Summary: 工具包
Author: zhaoxuefeng
Requires-Dist: tritonclient[all]
